pypiPracticeTest/test1.py
pypiPracticeTest/test2.py
pypiPractice-0.0.0.2.dist-info/METADATA
pypiPractice-0.0.0.2.dist-info/WHEEL
pypiPractice-0.0.0.2.dist-info/top_level.txt
pypiPractice-0.0.0.2.dist-info/RECORD
