Metadata-Version: 2.1
Name: pypiPractice
Version: 0.0.0.2
Summary: My First Test Package
Home-page: https://lingua.blog.me/...
Author: Jaeeun Kim
Author-email: kwh@gmail.com
License: MIT
Platform: UNKNOWN
Requires-Python: >=3
